appsecrets/__init__.py
appsecrets/api.py
appsecrets/cli.py
appsecrets/exc.py
appsecrets/py.typed
appsecrets/stores.py
appsecrets/crypto/__init__.py
appsecrets/crypto/dummy.py
appsecrets/crypto/google_kms.py
appsecrets-0.7.0.dist-info/LICENSE.txt
appsecrets-0.7.0.dist-info/METADATA
appsecrets-0.7.0.dist-info/RECORD
appsecrets-0.7.0.dist-info/WHEEL
appsecrets-0.7.0.dist-info/entry_points.txt
appsecrets-0.7.0.dist-info/top_level.txt
tests/__init__.py
tests/conftest.py
tests/functional/__init__.py
tests/functional/test_api.py
tests/integration/__init__.py
tests/integration/test_create.py
tests/integration/test_dummy.py
tests/integration/test_google_kms.py
tests/unittests/__init__.py
tests/unittests/test_google_kms.py
