Metadata-Version: 2.1
Name: appsecrets
Version: 0.7.0
Summary: Manage your application secrets (with Google Cloud KMS)
Home-page: https://github.com/pior/appsecrets
Author: Pior Bastida
Author-email: pior@pbastida.net
License: MIT
Keywords: secrets kms crypto
Platform: UNKNOWN
Classifier: Intended Audience :: Developers
Classifier: Programming Language :: Python
Classifier: Programming Language :: Python :: 3.6
Classifier: Programming Language :: Python :: 3.7
Classifier: License :: OSI Approved :: MIT License
Requires-Dist: google-api-python-client (~=1.7.0)
